boridge/__init__.py
boridge-0.1.9.dist-info/LICENSE
boridge-0.1.9.dist-info/METADATA
boridge-0.1.9.dist-info/WHEEL
boridge-0.1.9.dist-info/top_level.txt
boridge-0.1.9.dist-info/RECORD
