Metadata-Version: 2.1
Name: boridge
Version: 0.1.9
Summary: A library of functions for selecting features using bootstrapped ridge regression
Home-page: https://github.com/matthew-c-lenert/BoRidge
Author: MC Lenert
Author-email: matthew.c.lenert@gmail.com
License: MIT
Keywords: feature selection model evaluation
Platform: UNKNOWN
Classifier: Development Status :: 4 - Beta
Classifier: License :: OSI Approved :: MIT License
Classifier: Programming Language :: Python :: 3.6
Classifier: Topic :: Scientific/Engineering :: Information Analysis
Classifier: Topic :: Scientific/Engineering :: Medical Science Apps.
Requires-Dist: numpy
Requires-Dist: pandas
Requires-Dist: scipy
Requires-Dist: joblib
Requires-Dist: datetime
